fantasy_face/__init__.py
fantasy_face/fantasy_face.py
fantasy_face-1.0.0.dist-info/METADATA
fantasy_face-1.0.0.dist-info/WHEEL
fantasy_face-1.0.0.dist-info/top_level.txt
fantasy_face-1.0.0.dist-info/RECORD
