Metadata-Version: 2.1
Name: fantasy_face
Version: 1.0.0
Summary: Add an animal mask to the face
Home-page: https://github.com/SinaHosseini/amoo_sina_lion
Author: Sina Hosseini
Author-email: sshosseinivaez@gmail.com
